{
	"type":"root",
	"children":[
        {
			"type":"fixed_ratio_container",
			"x":0.0,
			"y":0.0,
			"w":1.0,
			"h":1.0,
			"align_h":"center",
			"align_v":"center",
			"visible":0,
			"enabled":0,
			"children":[
				{
					"type":"text_widget",
					"x":0.30,
					"y":0.10,
					"w":0.5,
					"h":0.1,
					"color":"0x660000",
					"visible":1,
					"enabled":0,
					"text":"Teleportin'...",
					"fontsize":6
				},
                {
                    "type":"image",
                    "x":0.0,
                    "y":0.20,
                    "w":1.0,
                    "h":0.65,
                    "color":"0xffffff",
                    "visible":1,
                    "enabled":0,
                    "actor_visual":"%%reaping_resurr_splash",
                    "fontsize":3
                }
			]
		},
		{
			"type":"fixed_ratio_container",
			"x":0.0,
			"y":0.0,
			"w":2.0,
			"h":1.0,
			"align_h":"left",
			"align_v":"center",
			"visible":0,
			"enabled":0,
			"children":[
                {
                    "type":"image",
                    "x":0.0,
                    "y":0.0,
                    "w":1.0,
                    "h":1.0,
                    "color":"0xffffff",
                    "visible":1,
                    "enabled":0,
                    "actor_visual":"%%black_background",
                    "fontsize":3
                }
			]
		}        
	]
}
